ctfl/__init__.py
ctfl/__main__.py
ctfl-2.0.4.dist-info/LICENSE
ctfl-2.0.4.dist-info/METADATA
ctfl-2.0.4.dist-info/WHEEL
ctfl-2.0.4.dist-info/entry_points.txt
ctfl-2.0.4.dist-info/top_level.txt
ctfl-2.0.4.dist-info/RECORD
