Metadata-Version: 2.1
Name: ctfl
Version: 2.0.4
Summary: CTFTime Upcoming CTF Lists
Home-page: https://github.com/thehackersbrain/ctfl
Author: Gaurav Raj
Author-email: techw803@gmail.com
License: MIT
Keywords: ctf,ctftime,thehackersbrain,gauravraj,python
License-File: LICENSE
Requires-Dist: rich
Requires-Dist: requests
Requires-Dist: bs4
